{"changedBlocks":[{"posX":15.0,"posY":14.0,"posZ":7.0,"blockId":9},{"posX":15.0,"posY":13.0,"posZ":7.0,"blockId":9},{"posX":14.0,"posY":14.0,"posZ":7.0,"blockId":0},{"posX":14.0,"posY":13.0,"posZ":7.0,"blockId":12},{"posX":13.0,"posY":14.0,"posZ":7.0,"blockId":0},{"posX":13.0,"posY":13.0,"posZ":7.0,"blockId":12},{"posX":12.0,"posY":14.0,"posZ":7.0,"blockId":0},{"posX":12.0,"posY":13.0,"posZ":7.0,"blockId":12},{"posX":11.0,"posY":13.0,"posZ":7.0,"blockId":12},{"posX":10.0,"posY":13.0,"posZ":7.0,"blockId":9},{"posX":15.0,"posY":15.0,"posZ":7.0,"blockId":9},{"posX":14.0,"posY":15.0,"posZ":7.0,"blockId":10},{"posX":13.0,"posY":15.0,"posZ":7.0,"blockId":10},{"posX":12.0,"posY":15.0,"posZ":7.0,"blockId":10},{"posX":11.0,"posY":15.0,"posZ":7.0,"blockId":10},{"posX":10.0,"posY":15.0,"posZ":7.0,"blockId":9},{"posX":11.0,"posY":14.0,"posZ":7.0,"blockId":0},{"posX":10.0,"posY":14.0,"posZ":7.0,"blockId":9},{"posX":15.0,"posY":14.0,"posZ":8.0,"blockId":0},{"posX":15.0,"posY":13.0,"posZ":8.0,"blockId":0},{"posX":14.0,"posY":14.0,"posZ":8.0,"blockId":0},{"posX":14.0,"posY":13.0,"posZ":8.0,"blockId":0},{"posX":13.0,"posY":14.0,"posZ":8.0,"blockId":0},{"posX":13.0,"posY":13.0,"posZ":8.0,"blockId":0},{"posX":12.0,"posY":14.0,"posZ":8.0,"blockId":0},{"posX":12.0,"posY":13.0,"posZ":8.0,"blockId":0},{"posX":11.0,"posY":14.0,"posZ":8.0,"blockId":0},{"posX":11.0,"posY":13.0,"posZ":8.0,"blockId":0},{"posX":10.0,"posY":14.0,"posZ":8.0,"blockId":0},{"posX":10.0,"posY":13.0,"posZ":8.0,"blockId":0},{"posX":15.0,"posY":13.0,"posZ":9.0,"blockId":0},{"posX":15.0,"posY":14.0,"posZ":9.0,"blockId":0},{"posX":14.0,"posY":13.0,"posZ":9.0,"blockId":0},{"posX":14.0,"posY":14.0,"posZ":9.0,"blockId":0},{"posX":13.0,"posY":13.0,"posZ":9.0,"blockId":0},{"posX":13.0,"posY":14.0,"posZ":9.0,"blockId":0},{"posX":12.0,"posY":13.0,"posZ":9.0,"blockId":0},{"posX":12.0,"posY":14.0,"posZ":9.0,"blockId":0},{"posX":11.0,"posY":14.0,"posZ":9.0,"blockId":0},{"posX":10.0,"posY":14.0,"posZ":9.0,"blockId":0},{"posX":15.0,"posY":14.0,"posZ":10.0,"blockId":0},{"posX":14.0,"posY":14.0,"posZ":10.0,"blockId":0},{"posX":15.0,"posY":13.0,"posZ":10.0,"blockId":0},{"posX":13.0,"posY":14.0,"posZ":10.0,"blockId":0},{"posX":12.0,"posY":14.0,"posZ":10.0,"blockId":0},{"posX":14.0,"posY":13.0,"posZ":10.0,"blockId":0},{"posX":11.0,"posY":14.0,"posZ":10.0,"blockId":0},{"posX":10.0,"posY":14.0,"posZ":10.0,"blockId":0},{"posX":9.0,"posY":14.0,"posZ":10.0,"blockId":14},{"posX":15.0,"posY":14.0,"posZ":11.0,"blockId":0},{"posX":15.0,"posY":13.0,"posZ":11.0,"blockId":0},{"posX":14.0,"posY":14.0,"posZ":11.0,"blockId":0},{"posX":13.0,"posY":14.0,"posZ":11.0,"blockId":0},{"posX":12.0,"posY":14.0,"posZ":11.0,"blockId":0},{"posX":11.0,"posY":14.0,"posZ":11.0,"blockId":0},{"posX":10.0,"posY":14.0,"posZ":11.0,"blockId":0},{"posX":15.0,"posY":14.0,"posZ":12.0,"blockId":0},{"posX":14.0,"posY":14.0,"posZ":12.0,"blockId":0},{"posX":13.0,"posY":14.0,"posZ":12.0,"blockId":0},{"posX":12.0,"posY":14.0,"posZ":12.0,"blockId":0},{"posX":11.0,"posY":14.0,"posZ":12.0,"blockId":0},{"posX":10.0,"posY":14.0,"posZ":12.0,"blockId":0},{"posX":15.0,"posY":14.0,"posZ":14.0,"blockId":0},{"posX":15.0,"posY":14.0,"posZ":13.0,"blockId":0},{"posX":14.0,"posY":14.0,"posZ":13.0,"blockId":0},{"posX":13.0,"posY":14.0,"posZ":13.0,"blockId":0},{"posX":14.0,"posY":14.0,"posZ":14.0,"blockId":0},{"posX":12.0,"posY":14.0,"posZ":13.0,"blockId":0},{"posX":11.0,"posY":14.0,"posZ":13.0,"blockId":0},{"posX":10.0,"posY":14.0,"posZ":13.0,"blockId":0},{"posX":13.0,"posY":14.0,"posZ":14.0,"blockId":0},{"posX":12.0,"posY":14.0,"posZ":14.0,"blockId":0},{"posX":11.0,"posY":14.0,"posZ":14.0,"blockId":0},{"posX":15.0,"posY":12.0,"posZ":7.0,"blockId":9},{"posX":15.0,"posY":12.0,"posZ":8.0,"blockId":9},{"posX":15.0,"posY":12.0,"posZ":9.0,"blockId":9},{"posX":14.0,"posY":12.0,"posZ":6.0,"blockId":9},{"posX":14.0,"posY":12.0,"posZ":7.0,"blockId":9},{"posX":14.0,"posY":12.0,"posZ":8.0,"blockId":9},{"posX":14.0,"posY":12.0,"posZ":9.0,"blockId":9},{"posX":13.0,"posY":12.0,"posZ":6.0,"blockId":9},{"posX":13.0,"posY":12.0,"posZ":7.0,"blockId":9},{"posX":13.0,"posY":12.0,"posZ":8.0,"blockId":9},{"posX":13.0,"posY":12.0,"posZ":9.0,"blockId":9},{"posX":12.0,"posY":12.0,"posZ":6.0,"blockId":9},{"posX":12.0,"posY":12.0,"posZ":7.0,"blockId":9},{"posX":12.0,"posY":12.0,"posZ":8.0,"blockId":9},{"posX":12.0,"posY":12.0,"posZ":9.0,"blockId":9},{"posX":11.0,"posY":12.0,"posZ":8.0,"blockId":9},{"posX":10.0,"posY":12.0,"posZ":8.0,"blockId":9},{"posX":11.0,"posY":12.0,"posZ":7.0,"blockId":9},{"posX":10.0,"posY":12.0,"posZ":7.0,"blockId":9},{"posX":11.0,"posY":12.0,"posZ":9.0,"blockId":9},{"posX":10.0,"posY":12.0,"posZ":9.0,"blockId":9},{"posX":15.0,"posY":12.0,"posZ":10.0,"blockId":9},{"posX":14.0,"posY":12.0,"posZ":10.0,"blockId":9},{"posX":13.0,"posY":12.0,"posZ":10.0,"blockId":9},{"posX":12.0,"posY":12.0,"posZ":10.0,"blockId":9},{"posX":11.0,"posY":12.0,"posZ":10.0,"blockId":9},{"posX":10.0,"posY":12.0,"posZ":10.0,"blockId":9},{"posX":13.0,"posY":12.0,"posZ":11.0,"blockId":9},{"posX":14.0,"posY":12.0,"posZ":11.0,"blockId":9},{"posX":15.0,"posY":12.0,"posZ":11.0,"blockId":9},{"posX":10.0,"posY":12.0,"posZ":11.0,"blockId":9},{"posX":11.0,"posY":12.0,"posZ":11.0,"blockId":9},{"posX":12.0,"posY":12.0,"posZ":11.0,"blockId":9},{"posX":9.0,"posY":13.0,"posZ":9.0,"blockId":14},{"posX":9.0,"posY":13.0,"posZ":10.0,"blockId":14},{"posX":15.0,"posY":12.0,"posZ":12.0,"blockId":9},{"posX":14.0,"posY":12.0,"posZ":12.0,"blockId":9},{"posX":14.0,"posY":12.0,"posZ":13.0,"blockId":9},{"posX":15.0,"posY":12.0,"posZ":13.0,"blockId":9},{"posX":14.0,"posY":12.0,"posZ":14.0,"blockId":9},{"posX":15.0,"posY":12.0,"posZ":14.0,"blockId":9},{"posX":10.0,"posY":12.0,"posZ":12.0,"blockId":9},{"posX":11.0,"posY":12.0,"posZ":12.0,"blockId":9},{"posX":12.0,"posY":12.0,"posZ":12.0,"blockId":9},{"posX":13.0,"posY":12.0,"posZ":12.0,"blockId":9},{"posX":10.0,"posY":12.0,"posZ":13.0,"blockId":9},{"posX":11.0,"posY":12.0,"posZ":13.0,"blockId":9},{"posX":12.0,"posY":12.0,"posZ":13.0,"blockId":9},{"posX":13.0,"posY":12.0,"posZ":13.0,"blockId":9},{"posX":13.0,"posY":12.0,"posZ":14.0,"blockId":9},{"posX":13.0,"posY":13.0,"posZ":14.0,"blockId":0},{"posX":12.0,"posY":12.0,"posZ":14.0,"blockId":9},{"posX":11.0,"posY":12.0,"posZ":14.0,"blockId":9},{"posX":10.0,"posY":12.0,"posZ":14.0,"blockId":9},{"posX":15.0,"posY":12.0,"posZ":15.0,"blockId":9},{"posX":14.0,"posY":12.0,"posZ":15.0,"blockId":9},{"posX":13.0,"posY":12.0,"posZ":15.0,"blockId":9},{"posX":12.0,"posY":12.0,"posZ":15.0,"blockId":9},{"posX":11.0,"posY":12.0,"posZ":15.0,"blockId":9},{"posX":10.0,"posY":12.0,"posZ":15.0,"blockId":9},{"posX":9.0,"posY":13.0,"posZ":11.0,"blockId":14},{"posX":9.0,"posY":13.0,"posZ":12.0,"blockId":14},{"posX":9.0,"posY":13.0,"posZ":13.0,"blockId":14},{"posX":9.0,"posY":13.0,"posZ":14.0,"blockId":14},{"posX":9.0,"posY":14.0,"posZ":15.0,"blockId":14},{"posX":9.0,"posY":13.0,"posZ":15.0,"blockId":14},{"posX":15.0,"posY":15.0,"posZ":8.0,"blockId":0},{"posX":14.0,"posY":15.0,"posZ":8.0,"blockId":0},{"posX":13.0,"posY":15.0,"posZ":8.0,"blockId":0},{"posX":12.0,"posY":15.0,"posZ":8.0,"blockId":0},{"posX":11.0,"posY":15.0,"posZ":8.0,"blockId":0},{"posX":10.0,"posY":15.0,"posZ":8.0,"blockId":0},{"posX":9.0,"posY":15.0,"posZ":8.0,"blockId":14},{"posX":11.0,"posY":15.0,"posZ":9.0,"blockId":0},{"posX":10.0,"posY":15.0,"posZ":9.0,"blockId":0},{"posX":12.0,"posY":15.0,"posZ":9.0,"blockId":0},{"posX":11.0,"posY":15.0,"posZ":10.0,"blockId":0},{"posX":10.0,"posY":15.0,"posZ":10.0,"blockId":0},{"posX":15.0,"posY":15.0,"posZ":9.0,"blockId":0},{"posX":14.0,"posY":15.0,"posZ":9.0,"blockId":0},{"posX":13.0,"posY":15.0,"posZ":9.0,"blockId":0},{"posX":10.0,"posY":15.0,"posZ":11.0,"blockId":0},{"posX":10.0,"posY":15.0,"posZ":12.0,"blockId":0},{"posX":10.0,"posY":15.0,"posZ":13.0,"blockId":0},{"posX":10.0,"posY":15.0,"posZ":14.0,"blockId":10},{"posX":10.0,"posY":15.0,"posZ":15.0,"blockId":9},{"posX":15.0,"posY":15.0,"posZ":10.0,"blockId":0},{"posX":15.0,"posY":15.0,"posZ":11.0,"blockId":0},{"posX":14.0,"posY":15.0,"posZ":11.0,"blockId":0},{"posX":14.0,"posY":15.0,"posZ":10.0,"blockId":0},{"posX":13.0,"posY":15.0,"posZ":11.0,"blockId":0},{"posX":11.0,"posY":15.0,"posZ":15.0,"blockId":10},{"posX":13.0,"posY":15.0,"posZ":10.0,"blockId":0},{"posX":12.0,"posY":15.0,"posZ":11.0,"blockId":0},{"posX":12.0,"posY":15.0,"posZ":10.0,"blockId":0},{"posX":12.0,"posY":15.0,"posZ":15.0,"blockId":0},{"posX":13.0,"posY":15.0,"posZ":15.0,"blockId":0},{"posX":12.0,"posY":15.0,"posZ":14.0,"blockId":0},{"posX":13.0,"posY":15.0,"posZ":14.0,"blockId":0},{"posX":14.0,"posY":15.0,"posZ":15.0,"blockId":0},{"posX":15.0,"posY":15.0,"posZ":12.0,"blockId":0},{"posX":15.0,"posY":15.0,"posZ":15.0,"blockId":0},{"posX":15.0,"posY":15.0,"posZ":13.0,"blockId":0},{"posX":14.0,"posY":15.0,"posZ":12.0,"blockId":0},{"posX":14.0,"posY":15.0,"posZ":13.0,"blockId":0},{"posX":13.0,"posY":15.0,"posZ":12.0,"blockId":0},{"posX":13.0,"posY":15.0,"posZ":13.0,"blockId":0},{"posX":15.0,"posY":15.0,"posZ":14.0,"blockId":0},{"posX":14.0,"posY":15.0,"posZ":14.0,"blockId":0},{"posX":11.0,"posY":15.0,"posZ":14.0,"blockId":0},{"posX":11.0,"posY":15.0,"posZ":13.0,"blockId":0},{"posX":12.0,"posY":15.0,"posZ":13.0,"blockId":0},{"posX":12.0,"posY":15.0,"posZ":12.0,"blockId":0},{"posX":11.0,"posY":15.0,"posZ":12.0,"blockId":0},{"posX":11.0,"posY":15.0,"posZ":11.0,"blockId":0},{"posX":15.0,"posY":13.0,"posZ":15.0,"blockId":0},{"posX":15.0,"posY":13.0,"posZ":14.0,"blockId":0},{"posX":10.0,"posY":13.0,"posZ":15.0,"blockId":9},{"posX":11.0,"posY":14.0,"posZ":15.0,"blockId":0},{"posX":10.0,"posY":14.0,"posZ":15.0,"blockId":9},{"posX":11.0,"posY":13.0,"posZ":15.0,"blockId":10},{"posX":10.0,"posY":13.0,"posZ":14.0,"blockId":10},{"posX":10.0,"posY":13.0,"posZ":13.0,"blockId":0},{"posX":10.0,"posY":13.0,"posZ":11.0,"blockId":0},{"posX":10.0,"posY":13.0,"posZ":12.0,"blockId":0},{"posX":11.0,"posY":13.0,"posZ":12.0,"blockId":0},{"posX":10.0,"posY":14.0,"posZ":14.0,"blockId":0},{"posX":9.0,"posY":14.0,"posZ":13.0,"blockId":14}],"usersChangedBlocks":[{"userName":" чай","changedBlocks":[{"posX":319.0,"posY":78.0,"posZ":327.0,"blockId":0},{"posX":319.0,"posY":77.0,"posZ":327.0,"blockId":0},{"posX":318.0,"posY":78.0,"posZ":327.0,"blockId":0},{"posX":318.0,"posY":77.0,"posZ":327.0,"blockId":0},{"posX":317.0,"posY":78.0,"posZ":327.0,"blockId":0},{"posX":317.0,"posY":77.0,"posZ":327.0,"blockId":0},{"posX":316.0,"posY":78.0,"posZ":327.0,"blockId":0},{"posX":316.0,"posY":77.0,"posZ":327.0,"blockId":0},{"posX":315.0,"posY":77.0,"posZ":327.0,"blockId":0},{"posX":314.0,"posY":77.0,"posZ":327.0,"blockId":0},{"posX":319.0,"posY":79.0,"posZ":327.0,"blockId":0},{"posX":318.0,"posY":79.0,"posZ":327.0,"blockId":10},{"posX":317.0,"posY":79.0,"posZ":327.0,"blockId":10},{"posX":316.0,"posY":79.0,"posZ":327.0,"blockId":10},{"posX":315.0,"posY":79.0,"posZ":327.0,"blockId":0},{"posX":314.0,"posY":79.0,"posZ":327.0,"blockId":0},{"posX":315.0,"posY":78.0,"posZ":327.0,"blockId":0},{"posX":314.0,"posY":78.0,"posZ":327.0,"blockId":0},{"posX":319.0,"posY":78.0,"posZ":328.0,"blockId":0},{"posX":319.0,"posY":77.0,"posZ":328.0,"blockId":0},{"posX":318.0,"posY":78.0,"posZ":328.0,"blockId":0},{"posX":318.0,"posY":77.0,"posZ":328.0,"blockId":0},{"posX":317.0,"posY":78.0,"posZ":328.0,"blockId":0},{"posX":317.0,"posY":77.0,"posZ":328.0,"blockId":0},{"posX":316.0,"posY":78.0,"posZ":328.0,"blockId":0},{"posX":316.0,"posY":77.0,"posZ":328.0,"blockId":0},{"posX":315.0,"posY":78.0,"posZ":328.0,"blockId":0},{"posX":315.0,"posY":77.0,"posZ":328.0,"blockId":0},{"posX":314.0,"posY":78.0,"posZ":328.0,"blockId":0},{"posX":314.0,"posY":77.0,"posZ":328.0,"blockId":0},{"posX":319.0,"posY":77.0,"posZ":329.0,"blockId":0},{"posX":319.0,"posY":78.0,"posZ":329.0,"blockId":0},{"posX":318.0,"posY":77.0,"posZ":329.0,"blockId":0},{"posX":318.0,"posY":78.0,"posZ":329.0,"blockId":0},{"posX":317.0,"posY":77.0,"posZ":329.0,"blockId":0},{"posX":317.0,"posY":78.0,"posZ":329.0,"blockId":0},{"posX":316.0,"posY":77.0,"posZ":329.0,"blockId":0},{"posX":316.0,"posY":78.0,"posZ":329.0,"blockId":0},{"posX":315.0,"posY":78.0,"posZ":329.0,"blockId":0},{"posX":314.0,"posY":78.0,"posZ":329.0,"blockId":0},{"posX":319.0,"posY":78.0,"posZ":330.0,"blockId":0},{"posX":318.0,"posY":78.0,"posZ":330.0,"blockId":0},{"posX":319.0,"posY":77.0,"posZ":330.0,"blockId":0},{"posX":317.0,"posY":78.0,"posZ":330.0,"blockId":0},{"posX":316.0,"posY":78.0,"posZ":330.0,"blockId":0},{"posX":318.0,"posY":77.0,"posZ":330.0,"blockId":0},{"posX":315.0,"posY":78.0,"posZ":330.0,"blockId":0},{"posX":314.0,"posY":78.0,"posZ":330.0,"blockId":0},{"posX":313.0,"posY":78.0,"posZ":330.0,"blockId":14},{"posX":319.0,"posY":78.0,"posZ":331.0,"blockId":0},{"posX":319.0,"posY":77.0,"posZ":331.0,"blockId":0},{"posX":318.0,"posY":78.0,"posZ":331.0,"blockId":0},{"posX":317.0,"posY":78.0,"posZ":331.0,"blockId":0},{"posX":316.0,"posY":78.0,"posZ":331.0,"blockId":0},{"posX":315.0,"posY":78.0,"posZ":331.0,"blockId":0},{"posX":314.0,"posY":78.0,"posZ":331.0,"blockId":0},{"posX":319.0,"posY":78.0,"posZ":332.0,"blockId":0},{"posX":318.0,"posY":78.0,"posZ":332.0,"blockId":0},{"posX":317.0,"posY":78.0,"posZ":332.0,"blockId":0},{"posX":316.0,"posY":78.0,"posZ":332.0,"blockId":0},{"posX":315.0,"posY":78.0,"posZ":332.0,"blockId":0},{"posX":314.0,"posY":78.0,"posZ":332.0,"blockId":0},{"posX":319.0,"posY":78.0,"posZ":334.0,"blockId":0},{"posX":319.0,"posY":78.0,"posZ":333.0,"blockId":0},{"posX":318.0,"posY":78.0,"posZ":333.0,"blockId":0},{"posX":317.0,"posY":78.0,"posZ":333.0,"blockId":0},{"posX":318.0,"posY":78.0,"posZ":334.0,"blockId":0},{"posX":316.0,"posY":78.0,"posZ":333.0,"blockId":0},{"posX":315.0,"posY":78.0,"posZ":333.0,"blockId":0},{"posX":314.0,"posY":78.0,"posZ":333.0,"blockId":0},{"posX":317.0,"posY":78.0,"posZ":334.0,"blockId":0},{"posX":316.0,"posY":78.0,"posZ":334.0,"blockId":0},{"posX":315.0,"posY":78.0,"posZ":334.0,"blockId":0},{"posX":319.0,"posY":76.0,"posZ":327.0,"blockId":9},{"posX":319.0,"posY":76.0,"posZ":328.0,"blockId":9},{"posX":319.0,"posY":76.0,"posZ":329.0,"blockId":9},{"posX":318.0,"posY":76.0,"posZ":326.0,"blockId":9},{"posX":318.0,"posY":76.0,"posZ":327.0,"blockId":9},{"posX":318.0,"posY":76.0,"posZ":328.0,"blockId":9},{"posX":318.0,"posY":76.0,"posZ":329.0,"blockId":9},{"posX":317.0,"posY":76.0,"posZ":326.0,"blockId":9},{"posX":317.0,"posY":76.0,"posZ":327.0,"blockId":9},{"posX":317.0,"posY":76.0,"posZ":328.0,"blockId":9},{"posX":317.0,"posY":76.0,"posZ":329.0,"blockId":9},{"posX":316.0,"posY":76.0,"posZ":326.0,"blockId":9},{"posX":316.0,"posY":76.0,"posZ":327.0,"blockId":9},{"posX":316.0,"posY":76.0,"posZ":328.0,"blockId":9},{"posX":316.0,"posY":76.0,"posZ":329.0,"blockId":9},{"posX":315.0,"posY":76.0,"posZ":328.0,"blockId":9},{"posX":314.0,"posY":76.0,"posZ":328.0,"blockId":9},{"posX":315.0,"posY":76.0,"posZ":327.0,"blockId":9},{"posX":314.0,"posY":76.0,"posZ":327.0,"blockId":9},{"posX":315.0,"posY":76.0,"posZ":329.0,"blockId":9},{"posX":314.0,"posY":76.0,"posZ":329.0,"blockId":9},{"posX":319.0,"posY":76.0,"posZ":330.0,"blockId":9},{"posX":318.0,"posY":76.0,"posZ":330.0,"blockId":9},{"posX":317.0,"posY":76.0,"posZ":330.0,"blockId":9},{"posX":316.0,"posY":76.0,"posZ":330.0,"blockId":9},{"posX":315.0,"posY":76.0,"posZ":330.0,"blockId":9},{"posX":314.0,"posY":76.0,"posZ":330.0,"blockId":9},{"posX":313.0,"posY":77.0,"posZ":329.0,"blockId":14},{"posX":313.0,"posY":77.0,"posZ":330.0,"blockId":14},{"posX":319.0,"posY":76.0,"posZ":332.0,"blockId":9},{"posX":318.0,"posY":76.0,"posZ":332.0,"blockId":9},{"posX":317.0,"posY":76.0,"posZ":334.0,"blockId":9},{"posX":317.0,"posY":77.0,"posZ":334.0,"blockId":0},{"posX":316.0,"posY":76.0,"posZ":334.0,"blockId":9},{"posX":315.0,"posY":76.0,"posZ":334.0,"blockId":9},{"posX":314.0,"posY":76.0,"posZ":334.0,"blockId":9},{"posX":319.0,"posY":76.0,"posZ":335.0,"blockId":9},{"posX":318.0,"posY":76.0,"posZ":335.0,"blockId":9},{"posX":317.0,"posY":76.0,"posZ":335.0,"blockId":9},{"posX":316.0,"posY":76.0,"posZ":335.0,"blockId":9},{"posX":315.0,"posY":76.0,"posZ":335.0,"blockId":9},{"posX":314.0,"posY":76.0,"posZ":335.0,"blockId":9},{"posX":313.0,"posY":77.0,"posZ":331.0,"blockId":14},{"posX":313.0,"posY":77.0,"posZ":332.0,"blockId":14},{"posX":313.0,"posY":77.0,"posZ":333.0,"blockId":14},{"posX":313.0,"posY":77.0,"posZ":334.0,"blockId":14},{"posX":313.0,"posY":78.0,"posZ":335.0,"blockId":14},{"posX":313.0,"posY":77.0,"posZ":335.0,"blockId":14},{"posX":317.0,"posY":79.0,"posZ":328.0,"blockId":0},{"posX":315.0,"posY":79.0,"posZ":328.0,"blockId":0},{"posX":313.0,"posY":79.0,"posZ":328.0,"blockId":0},{"posX":319.0,"posY":79.0,"posZ":329.0,"blockId":0},{"posX":318.0,"posY":79.0,"posZ":329.0,"blockId":0},{"posX":317.0,"posY":79.0,"posZ":329.0,"blockId":0},{"posX":319.0,"posY":79.0,"posZ":330.0,"blockId":0},{"posX":319.0,"posY":79.0,"posZ":331.0,"blockId":0},{"posX":318.0,"posY":79.0,"posZ":331.0,"blockId":0},{"posX":318.0,"posY":79.0,"posZ":330.0,"blockId":0},{"posX":317.0,"posY":79.0,"posZ":331.0,"blockId":0},{"posX":317.0,"posY":79.0,"posZ":330.0,"blockId":0},{"posX":316.0,"posY":79.0,"posZ":331.0,"blockId":0},{"posX":316.0,"posY":79.0,"posZ":330.0,"blockId":0},{"posX":319.0,"posY":79.0,"posZ":332.0,"blockId":0},{"posX":319.0,"posY":79.0,"posZ":333.0,"blockId":0},{"posX":318.0,"posY":79.0,"posZ":332.0,"blockId":0},{"posX":318.0,"posY":79.0,"posZ":333.0,"blockId":0},{"posX":317.0,"posY":79.0,"posZ":332.0,"blockId":0},{"posX":317.0,"posY":79.0,"posZ":333.0,"blockId":0},{"posX":318.0,"posY":79.0,"posZ":334.0,"blockId":0},{"posX":315.0,"posY":79.0,"posZ":335.0,"blockId":10},{"posX":315.0,"posY":77.0,"posZ":335.0,"blockId":10},{"posX":314.0,"posY":77.0,"posZ":334.0,"blockId":10},{"posX":315.0,"posY":79.0,"posZ":334.0,"blockId":0},{"posX":314.0,"posY":79.0,"posZ":334.0,"blockId":10},{"posX":314.0,"posY":77.0,"posZ":331.0,"blockId":0},{"posX":314.0,"posY":77.0,"posZ":332.0,"blockId":0},{"posX":315.0,"posY":77.0,"posZ":332.0,"blockId":0},{"posX":314.0,"posY":77.0,"posZ":333.0,"blockId":0},{"posX":314.0,"posY":78.0,"posZ":334.0,"blockId":0},{"posX":313.0,"posY":78.0,"posZ":333.0,"blockId":14}]},{"userName":"Сухарик","changedBlocks":[{"posX":317.0,"posY":76.0,"posZ":331.0,"blockId":9},{"posX":318.0,"posY":76.0,"posZ":331.0,"blockId":9},{"posX":319.0,"posY":76.0,"posZ":331.0,"blockId":9},{"posX":314.0,"posY":76.0,"posZ":331.0,"blockId":9},{"posX":315.0,"posY":76.0,"posZ":331.0,"blockId":9},{"posX":316.0,"posY":76.0,"posZ":331.0,"blockId":9},{"posX":318.0,"posY":76.0,"posZ":333.0,"blockId":9},{"posX":319.0,"posY":76.0,"posZ":333.0,"blockId":9},{"posX":318.0,"posY":76.0,"posZ":334.0,"blockId":9},{"posX":319.0,"posY":76.0,"posZ":334.0,"blockId":9},{"posX":314.0,"posY":76.0,"posZ":332.0,"blockId":9},{"posX":315.0,"posY":76.0,"posZ":332.0,"blockId":9},{"posX":316.0,"posY":76.0,"posZ":332.0,"blockId":9},{"posX":317.0,"posY":76.0,"posZ":332.0,"blockId":9},{"posX":314.0,"posY":76.0,"posZ":333.0,"blockId":9},{"posX":315.0,"posY":76.0,"posZ":333.0,"blockId":9},{"posX":316.0,"posY":76.0,"posZ":333.0,"blockId":9},{"posX":317.0,"posY":76.0,"posZ":333.0,"blockId":9},{"posX":319.0,"posY":79.0,"posZ":328.0,"blockId":0},{"posX":318.0,"posY":79.0,"posZ":328.0,"blockId":0},{"posX":317.0,"posY":79.0,"posZ":328.0,"blockId":0},{"posX":316.0,"posY":79.0,"posZ":328.0,"blockId":0},{"posX":315.0,"posY":79.0,"posZ":328.0,"blockId":0},{"posX":314.0,"posY":79.0,"posZ":328.0,"blockId":0},{"posX":315.0,"posY":79.0,"posZ":329.0,"blockId":0},{"posX":314.0,"posY":79.0,"posZ":329.0,"blockId":0},{"posX":316.0,"posY":79.0,"posZ":329.0,"blockId":0},{"posX":315.0,"posY":79.0,"posZ":330.0,"blockId":0},{"posX":314.0,"posY":79.0,"posZ":330.0,"blockId":0},{"posX":313.0,"posY":79.0,"posZ":328.0,"blockId":14},{"posX":314.0,"posY":79.0,"posZ":331.0,"blockId":0},{"posX":314.0,"posY":79.0,"posZ":332.0,"blockId":0},{"posX":314.0,"posY":79.0,"posZ":333.0,"blockId":0},{"posX":314.0,"posY":79.0,"posZ":334.0,"blockId":0},{"posX":314.0,"posY":79.0,"posZ":335.0,"blockId":9},{"posX":315.0,"posY":79.0,"posZ":335.0,"blockId":0},{"posX":316.0,"posY":79.0,"posZ":335.0,"blockId":0},{"posX":317.0,"posY":79.0,"posZ":335.0,"blockId":0},{"posX":316.0,"posY":79.0,"posZ":334.0,"blockId":0},{"posX":317.0,"posY":79.0,"posZ":334.0,"blockId":0},{"posX":318.0,"posY":79.0,"posZ":335.0,"blockId":0},{"posX":319.0,"posY":79.0,"posZ":335.0,"blockId":0},{"posX":319.0,"posY":79.0,"posZ":334.0,"blockId":0},{"posX":315.0,"posY":79.0,"posZ":334.0,"blockId":0},{"posX":315.0,"posY":79.0,"posZ":333.0,"blockId":0},{"posX":316.0,"posY":79.0,"posZ":333.0,"blockId":0},{"posX":316.0,"posY":79.0,"posZ":332.0,"blockId":0},{"posX":315.0,"posY":79.0,"posZ":332.0,"blockId":0},{"posX":315.0,"posY":79.0,"posZ":331.0,"blockId":0},{"posX":319.0,"posY":77.0,"posZ":335.0,"blockId":0},{"posX":319.0,"posY":77.0,"posZ":334.0,"blockId":0},{"posX":314.0,"posY":77.0,"posZ":335.0,"blockId":9},{"posX":315.0,"posY":78.0,"posZ":335.0,"blockId":0},{"posX":317.0,"posY":77.0,"posZ":327.0,"blockId":12},{"posX":316.0,"posY":77.0,"posZ":327.0,"blockId":12},{"posX":315.0,"posY":77.0,"posZ":327.0,"blockId":12},{"posX":318.0,"posY":77.0,"posZ":327.0,"blockId":12},{"posX":314.0,"posY":78.0,"posZ":335.0,"blockId":9},{"posX":314.0,"posY":77.0,"posZ":327.0,"blockId":9},{"posX":314.0,"posY":78.0,"posZ":327.0,"blockId":9},{"posX":314.0,"posY":79.0,"posZ":327.0,"blockId":9},{"posX":319.0,"posY":77.0,"posZ":327.0,"blockId":9},{"posX":319.0,"posY":78.0,"posZ":327.0,"blockId":9},{"posX":319.0,"posY":79.0,"posZ":327.0,"blockId":9},{"posX":315.0,"posY":79.0,"posZ":327.0,"blockId":10},{"posX":314.0,"posY":77.0,"posZ":333.0,"blockId":51},{"posX":314.0,"posY":77.0,"posZ":331.0,"blockId":0},{"posX":314.0,"posY":77.0,"posZ":332.0,"blockId":50}]}],"blocks":[[[0,0,0,0,0,0,0,0,0,0,0,0,14,14,14,14],[0,0,0,0,0,0,0,0,0,0,0,0,0,14,14,14],[0,0,0,0,0,0,0,0,0,0,0,0,0,0,14,14],[0,0,0,0,0,0,0,0,0,0,0,0,0,0,0,14],[0,0,0,0,0,0,0,0,0,0,0,0,0,0,0,14],[0,0,0,0,0,0,0,0,0,0,0,0,0,0,0,0],[0,0,0,0,0,0,0,0,0,0,0,0,0,0,0,0],[0,0,0,0,0,0,0,0,0,0,0,0,0,0,0,0],[0,0,0,0,0,0,0,0,0,0,0,0,0,0,0,0],[0,0,0,0,0,0,0,0,0,0,0,0,0,0,0,0],[0,0,0,0,0,0,0,0,0,0,0,0,0,0,0,0],[0,0,0,0,0,0,0,0,0,0,0,0,0,0,0,0],[0,0,0,0,0,14,14,14,14,14,14,14,14,14,14,0],[0,0,0,0,0,0,14,14,14,14,14,14,14,14,14,14],[0,0,0,0,0,0,0,14,14,14,14,14,14,14,14,14],[0,0,0,0,0,0,0,14,14,14,14,14,14,14,14,14]],[[0,0,0,0,0,0,0,0,0,0,0,0,0,14,14,14],[0,0,0,0,0,0,0,0,0,0,0,0,0,0,14,14],[0,0,0,0,0,0,0,0,0,0,0,0,0,0,0,14],[0,0,0,0,0,0,0,0,0,0,0,0,0,0,0,0],[0,0,0,0,0,0,0,0,0,0,0,0,0,0,0,0],[0,0,0,0,0,0,0,0,0,0,0,0,0,0,0,0],[0,0,0,0,0,0,0,0,0,0,0,0,0,0,0,0],[0,0,0,0,0,0,0,0,0,0,0,0,0,0,0,0],[0,0,0,0,0,0,0,0,0,0,0,0,0,0,0,0],[0,0,0,0,0,0,0,0,0,0,0,0,0,0,0,0],[0,0,0,0,0,0,0,0,0,0,0,0,0,0,0,0],[0,0,0,0,0,0,0,0,0,0,0,0,0,0,0,0],[0,0,0,0,14,14,14,14,0,0,0,0,0,0,0,0],[0,0,0,0,0,14,14,14,14,14,14,14,14,14,14,14],[0,0,0,0,0,0,14,14,14,14,14,14,14,14,14,14],[0,0,0,0,0,0,14,14,14,14,14,14,14,14,14,14]],[[0,0,0,0,0,0,0,0,0,0,0,0,0,0,14,14],[0,0,0,0,0,0,0,0,0,0,0,0,0,0,0,14],[0,0,0,0,0,0,0,0,0,0,0,0,0,0,0,0],[0,0,0,0,0,0,0,0,0,0,0,0,0,0,0,0],[0,0,0,0,0,0,0,0,0,0,0,0,0,0,0,0],[0,0,0,0,0,0,0,0,0,0,0,0,0,0,0,0],[0,0,0,0,0,0,0,0,0,0,0,0,0,0,0,0],[0,0,0,0,0,0,0,0,0,0,0,0,0,0,0,0],[0,0,0,0,0,0,0,0,0,0,0,0,0,0,0,0],[0,0,0,0,0,0,0,0,0,0,0,0,0,0,0,0],[0,0,0,0,0,0,0,0,0,0,0,0,0,0,0,0],[0,0,0,14,0,0,0,0,0,0,0,0,0,0,0,0],[0,0,0,0,14,14,14,0,0,0,0,0,0,0,0,0],[0,0,0,0,14,14,14,14,14,14,14,14,14,14,0,0],[0,0,0,0,0,14,14,14,14,14,14,14,14,14,14,14],[0,0,0,0,0,0,14,14,14,14,14,14,14,14,14,14]],[[0,0,0,0,0,0,0,0,0,0,0,0,0,0,14,14],[0,0,0,0,0,0,0,0,0,0,0,0,0,0,0,14],[0,0,0,0,0,0,0,0,0,0,0,0,0,0,0,0],[0,0,0,0,0,0,0,0,0,0,0,0,0,0,0,0],[0,0,0,0,0,0,0,0,0,0,0,0,0,0,0,0],[0,0,0,0,0,0,0,0,0,0,0,0,0,0,0,0],[0,0,0,0,0,0,0,0,0,0,0,0,0,0,0,0],[0,0,0,0,0,0,0,0,0,0,0,0,0,0,0,0],[0,0,0,0,0,0,0,0,0,0,0,0,0,0,0,0],[0,0,0,0,0,0,0,0,0,0,0,0,0,0,0,0],[0,0,0,0,0,0,0,0,0,0,0,0,0,0,0,0],[0,0,14,0,0,0,0,0,0,0,0,0,0,0,0,0],[0,0,0,14,14,14,0,0,0,0,0,0,0,0,0,0],[0,0,0,0,14,14,14,14,14,14,14,14,0,0,0,0],[0,0,0,0,14,14,14,14,14,14,14,14,14,14,14,14],[0,0,0,0,0,14,14,14,14,14,14,14,14,14,14,14]],[[0,0,0,0,0,0,0,0,0,0,0,0,0,0,0,14],[0,0,0,0,0,0,0,0,0,0,0,0,0,0,0,0],[0,0,0,0,0,0,0,0,0,0,0,0,0,0,0,0],[0,0,0,0,0,0,0,0,0,0,0,0,0,0,0,0],[0,0,0,0,0,0,0,0,0,0,0,0,0,0,0,0],[0,0,0,0,0,0,0,0,0,0,0,0,0,0,0,0],[0,0,0,0,0,0,0,0,0,0,0,0,0,0,0,0],[0,0,0,0,0,0,0,0,0,0,0,0,0,0,0,0],[0,0,0,0,0,0,0,0,0,0,0,0,0,0,0,0],[0,0,0,0,0,0,0,0,0,0,0,0,0,0,0,0],[0,0,0,0,0,0,0,0,0,0,0,0,0,0,0,0],[0,0,14,0,0,0,0,0,0,0,0,0,0,0,0,0],[0,0,14,14,14,14,0,0,0,0,0,0,0,0,0,0],[0,0,0,14,14,14,14,14,14,14,0,0,0,0,0,0],[0,0,0,0,14,14,14,14,14,14,14,14,14,14,14,14],[0,0,0,0,14,14,14,14,14,14,14,14,14,14,14,14]],[[0,0,0,0,0,0,0,0,0,0,0,0,0,0,0,0],[0,0,0,0,0,0,0,0,0,0,0,0,0,0,0,0],[0,0,0,0,0,0,0,0,0,0,0,0,0,0,0,0],[0,0,0,0,0,0,0,0,0,0,0,0,0,0,0,0],[0,0,0,0,0,0,0,0,0,0,0,0,0,0,0,0],[0,0,0,0,0,0,0,0,0,0,0,0,0,0,0,0],[0,0,0,0,0,0,0,0,0,0,0,0,0,0,0,0],[0,0,0,0,0,0,0,0,0,0,0,0,0,0,0,0],[0,0,0,0,0,0,0,0,0,0,0,0,0,0,0,0],[0,0,0,0,0,0,0,0,0,0,0,0,0,0,0,0],[14,0,0,0,0,0,0,0,0,0,0,0,0,0,0,0],[0,14,14,0,0,0,0,0,0,0,0,0,0,0,0,0],[0,0,14,14,14,0,0,0,0,0,0,0,0,0,0,0],[0,0,14,14,14,14,14,14,14,0,0,0,0,0,0,0],[0,0,0,14,14,14,14,14,14,14,14,14,14,14,14,14],[0,0,0,0,14,14,14,14,14,14,14,14,14,14,14,14]],[[0,0,0,0,0,0,0,0,0,0,0,0,0,0,0,0],[0,0,0,0,0,0,0,0,0,0,0,0,0,0,0,0],[0,0,0,0,0,0,0,0,0,0,0,0,0,0,0,0],[0,0,0,0,0,0,0,0,0,0,0,0,0,0,0,0],[0,0,0,0,0,0,0,0,0,0,0,0,0,0,0,0],[0,0,0,0,0,0,0,0,0,0,0,0,0,0,0,0],[0,0,0,0,0,0,0,0,0,0,0,0,0,0,0,0],[0,0,0,0,0,0,0,0,0,0,0,0,0,0,0,0],[0,0,0,0,0,0,0,0,0,0,0,0,0,0,0,0],[0,0,0,0,0,0,0,0,0,0,0,0,0,0,0,0],[14,0,0,0,0,0,0,0,0,0,0,0,0,0,0,0],[0,14,14,0,0,0,0,0,0,0,0,0,0,0,0,0],[0,14,14,14,14,0,0,0,0,0,0,0,0,0,0,0],[0,0,14,14,14,14,14,14,14,0,0,0,0,0,0,0],[0,0,0,14,14,14,14,14,14,14,14,14,14,14,14,0],[0,0,0,14,14,14,14,14,14,14,14,14,14,14,14,14]],[[0,0,0,0,0,0,0,0,0,0,0,0,0,0,0,0],[0,0,0,0,0,0,0,0,0,0,0,0,0,0,0,0],[0,0,0,0,0,0,0,0,0,0,0,0,0,0,0,0],[0,0,0,0,0,0,0,0,0,0,0,0,0,0,0,0],[0,0,0,0,0,0,0,0,0,0,0,0,0,0,0,0],[0,0,0,0,0,0,0,0,0,0,0,0,0,0,0,0],[0,0,0,0,0,0,0,0,0,0,0,0,0,0,0,0],[0,0,0,0,0,0,0,0,0,0,0,0,0,0,0,0],[0,0,0,0,0,0,0,0,0,0,0,0,0,0,0,0],[0,0,0,0,0,0,0,0,0,0,0,0,0,0,0,0],[14,0,0,0,0,0,0,0,0,0,0,0,0,0,0,0],[14,14,14,0,0,0,0,0,0,0,0,0,0,0,0,0],[0,14,14,14,14,0,0,0,0,0,0,0,0,0,0,0],[0,0,14,14,14,14,14,14,14,0,0,0,0,0,0,0],[0,0,14,14,14,14,14,14,14,14,14,14,14,14,14,0],[0,0,0,14,14,14,14,14,14,14,14,14,14,14,14,14]],[[0,0,0,0,0,0,0,0,0,0,0,0,0,0,0,0],[0,0,0,0,0,0,0,0,0,0,0,0,0,0,0,0],[0,0,0,0,0,0,0,0,0,0,0,0,0,0,0,0],[0,0,0,0,0,0,0,0,0,0,0,0,0,0,0,0],[0,0,0,0,0,0,0,0,0,0,0,0,0,0,0,0],[0,0,0,0,0,0,0,0,0,0,0,0,0,0,0,0],[0,0,0,0,0,0,0,0,0,0,0,0,0,0,0,0],[0,0,0,0,0,0,0,0,0,0,0,0,0,0,0,0],[0,0,0,0,0,0,0,0,0,0,0,0,0,0,0,0],[0,0,0,0,0,0,0,0,0,0,0,0,0,0,0,0],[14,0,0,0,0,0,0,0,0,0,0,0,0,0,0,0],[14,14,0,0,0,0,0,0,0,0,0,0,0,0,0,0],[14,14,14,14,14,0,0,0,0,0,0,0,0,0,0,0],[0,14,14,14,14,14,14,14,14,0,0,0,0,0,0,0],[0,0,14,14,14,14,14,14,14,14,14,14,14,14,14,0],[0,0,0,14,14,14,14,14,14,14,14,14,14,14,14,14]],[[0,0,0,0,0,0,0,0,0,0,0,0,0,0,0,0],[0,0,0,0,0,0,0,0,0,0,0,0,0,0,0,0],[0,0,0,0,0,0,0,0,0,0,0,0,0,0,0,0],[0,0,0,0,0,0,0,0,0,0,0,0,0,0,0,0],[0,0,0,0,0,0,0,0,0,0,0,0,0,0,0,0],[0,0,0,0,0,0,0,0,0,0,0,0,0,0,0,0],[0,0,0,0,0,0,0,0,0,0,0,0,0,0,0,0],[0,0,0,0,0,0,0,0,0,0,0,0,0,0,0,0],[0,0,0,0,0,0,0,0,0,0,0,0,0,0,0,0],[0,0,0,0,0,0,0,0,0,0,0,0,0,0,0,0],[14,0,0,0,0,0,0,0,0,0,0,0,0,0,0,0],[14,14,14,0,0,0,0,0,0,0,0,0,0,0,0,0],[14,14,14,14,14,0,0,0,0,0,0,0,0,0,0,0],[0,14,14,14,14,14,14,14,14,0,0,0,0,0,0,0],[0,0,14,14,14,14,14,14,14,14,14,14,14,14,14,0],[0,0,14,14,14,14,14,14,14,14,14,14,14,14,14,14]],[[0,0,0,0,0,0,0,0,0,0,0,0,0,0,0,0],[0,0,0,0,0,0,0,0,0,0,0,0,0,0,0,0],[0,0,0,0,0,0,0,0,0,0,0,0,0,0,0,0],[0,0,0,0,0,0,0,0,0,0,0,0,0,0,0,0],[0,0,0,0,0,0,0,0,0,0,0,0,0,0,0,0],[0,0,0,0,0,0,0,0,0,0,0,0,0,0,0,0],[0,0,0,0,0,0,0,0,0,0,0,0,0,0,0,0],[0,0,0,0,0,0,0,0,0,0,0,0,0,0,0,0],[0,0,0,0,0,0,0,0,0,0,0,0,0,0,0,0],[0,0,0,0,0,0,0,0,0,0,0,0,0,0,0,0],[14,0,0,0,0,0,0,0,0,0,0,0,0,0,0,0],[14,14,14,0,0,0,0,0,0,0,0,0,0,0,0,0],[14,14,14,14,14,0,0,0,0,0,0,0,0,0,0,0],[0,14,14,14,14,14,14,14,14,0,0,0,0,0,0,0],[0,14,14,14,14,14,14,14,14,14,14,14,14,14,0,0],[0,0,14,14,14,14,14,14,14,14,14,14,14,14,14,14]],[[0,0,0,0,0,0,0,0,0,0,0,0,0,0,0,0],[0,0,0,0,0,0,0,0,0,0,0,0,0,0,0,0],[0,0,0,0,0,0,0,0,0,0,0,0,0,0,0,0],[0,0,0,0,0,0,0,0,0,0,0,0,0,0,0,0],[0,0,0,0,0,0,0,0,0,0,0,0,0,0,0,0],[0,0,0,0,0,0,0,0,0,0,0,0,0,0,0,0],[0,0,0,0,0,0,0,0,0,0,0,0,0,0,0,0],[0,0,0,0,0,0,0,0,0,0,0,0,0,0,0,0],[0,0,0,0,0,0,0,0,0,0,0,0,0,0,0,0],[0,0,0,0,0,0,0,0,0,0,0,0,0,0,0,0],[14,0,0,0,0,0,0,0,0,0,0,0,0,0,0,0],[14,14,14,0,0,0,0,0,0,0,0,0,0,0,0,0],[14,14,14,14,14,0,0,0,0,0,0,0,0,0,0,0],[14,14,14,14,14,14,14,14,14,0,0,0,0,0,0,0],[0,14,14,14,14,14,14,14,14,14,14,14,14,14,14,0],[0,0,14,14,14,14,14,14,14,14,14,14,14,14,14,14]],[[0,0,0,0,0,0,0,0,0,0,0,0,0,0,0,0],[0,0,0,0,0,0,0,0,0,0,0,0,0,0,0,0],[0,0,0,0,0,0,0,0,0,0,0,0,0,0,0,0],[0,0,0,0,0,0,0,0,0,0,0,0,0,0,0,0],[0,0,0,0,0,0,0,0,0,0,0,0,0,0,0,0],[0,0,0,0,0,0,0,0,0,0,0,0,0,0,0,0],[0,0,0,0,0,0,0,0,0,0,0,0,0,0,0,0],[0,0,0,0,0,0,0,0,0,0,0,0,0,0,0,0],[0,0,0,0,0,0,0,0,0,0,0,0,0,0,0,0],[0,0,0,0,0,0,0,0,0,0,0,0,0,0,0,0],[14,0,0,0,0,0,0,0,0,0,0,0,0,0,0,0],[14,14,14,0,0,0,0,0,0,0,0,0,0,0,0,0],[14,14,14,14,14,14,0,0,0,0,0,0,0,0,0,0],[14,14,14,14,14,14,14,14,14,14,0,0,0,0,0,0],[0,14,14,14,14,14,14,14,14,14,14,14,14,14,14,0],[0,0,14,14,14,14,14,14,14,14,14,14,14,14,14,14]],[[0,0,0,0,0,0,0,0,0,0,0,0,0,0,0,0],[0,0,0,0,0,0,0,0,0,0,0,0,0,0,0,0],[0,0,0,0,0,0,0,0,0,0,0,0,0,0,0,0],[0,0,0,0,0,0,0,0,0,0,0,0,0,0,0,0],[0,0,0,0,0,0,0,0,0,0,0,0,0,0,0,0],[0,0,0,0,0,0,0,0,0,0,0,0,0,0,0,0],[0,0,0,0,0,0,0,0,0,0,0,0,0,0,0,0],[0,0,0,0,0,0,0,0,0,0,0,0,0,0,0,0],[0,0,0,0,0,0,0,0,0,0,0,0,0,0,0,0],[0,0,0,0,0,0,0,0,0,0,0,0,0,0,0,0],[14,0,0,0,0,0,0,0,0,0,0,0,0,0,0,0],[14,14,14,0,0,0,0,0,0,0,0,0,0,0,0,0],[14,14,14,14,14,14,0,0,0,0,0,0,0,0,0,0],[14,14,14,14,14,14,14,14,14,14,0,0,0,0,0,0],[0,14,14,14,14,14,14,14,14,14,14,14,14,14,14,0],[0,0,14,14,14,14,14,14,14,14,14,14,14,14,14,14]],[[0,0,0,0,0,0,0,0,0,0,0,0,0,0,0,0],[0,0,0,0,0,0,0,0,0,0,0,0,0,0,0,0],[0,0,0,0,0,0,0,0,0,0,0,0,0,0,0,0],[0,0,0,0,0,0,0,0,0,0,0,0,0,0,0,0],[0,0,0,0,0,0,0,0,0,0,0,0,0,0,0,0],[0,0,0,0,0,0,0,0,0,0,0,0,0,0,0,0],[0,0,0,0,0,0,0,0,0,0,0,0,0,0,0,0],[0,0,0,0,0,0,0,0,0,0,0,0,0,0,0,0],[0,0,0,0,0,0,0,0,0,0,0,0,0,0,0,0],[0,0,0,0,0,0,0,0,0,0,0,0,0,0,0,0],[14,0,0,0,0,0,0,0,0,0,0,0,0,0,0,0],[14,14,14,14,0,0,0,0,0,0,0,0,0,0,0,0],[14,14,14,14,14,14,0,0,0,0,0,0,0,0,0,0],[14,14,14,14,14,14,14,14,14,14,14,0,0,0,0,0],[0,14,14,14,14,14,14,14,14,14,14,14,14,14,14,0],[0,0,14,14,14,14,14,14,14,14,14,14,14,14,14,14]],[[0,0,0,0,0,0,0,0,0,0,0,0,0,0,0,0],[0,0,0,0,0,0,0,0,0,0,0,0,0,0,0,0],[0,0,0,0,0,0,0,0,0,0,0,0,0,0,0,0],[0,0,0,0,0,0,0,0,0,0,0,0,0,0,0,0],[0,0,0,0,0,0,0,0,0,0,0,0,0,0,0,0],[0,0,0,0,0,0,0,0,0,0,0,0,0,0,0,0],[0,0,0,0,0,0,0,0,0,0,0,0,0,0,0,0],[0,0,0,0,0,0,0,0,0,0,0,0,0,0,0,0],[0,0,0,0,0,0,0,0,0,0,0,0,0,0,0,0],[0,0,0,0,0,0,0,0,0,0,0,0,0,0,0,0],[14,14,0,0,0,0,0,0,0,0,0,0,0,0,0,0],[14,14,14,14,0,0,0,0,0,0,0,0,0,0,0,0],[14,14,14,14,14,14,14,0,0,0,0,0,0,0,0,0],[14,14,14,14,14,14,14,14,14,14,14,14,0,0,0,0],[0,14,14,14,14,14,14,14,14,14,14,14,14,14,14,0],[0,14,14,14,14,14,14,14,14,14,14,14,14,14,14,14]]],"turnedBlocks":[{"posX":13.0,"posY":13.0,"posZ":7.0,"turnsBlockData":[{"angle":0.0,"axis":2}]},{"posX":12.0,"posY":13.0,"posZ":7.0,"turnsBlockData":[{"angle":0.0,"axis":2}]},{"posX":11.0,"posY":13.0,"posZ":7.0,"turnsBlockData":[{"angle":0.0,"axis":2}]},{"posX":14.0,"posY":13.0,"posZ":7.0,"turnsBlockData":[{"angle":0.0,"axis":2}]}]}