{"blocksData":{"userName":"Скиталец 301","changedBlocks":[{"posX":0.0,"posY":0.0,"posZ":0.0,"blockId":2},{"posX":0.0,"posY":0.0,"posZ":1.0,"blockId":2},{"posX":0.0,"posY":0.0,"posZ":2.0,"blockId":2},{"posX":0.0,"posY":0.0,"posZ":3.0,"blockId":2},{"posX":0.0,"posY":1.0,"posZ":0.0,"blockId":2},{"posX":0.0,"posY":1.0,"posZ":1.0,"blockId":2},{"posX":0.0,"posY":1.0,"posZ":2.0,"blockId":2},{"posX":0.0,"posY":1.0,"posZ":3.0,"blockId":2},{"posX":0.0,"posY":2.0,"posZ":2.0,"blockId":1},{"posX":0.0,"posY":2.0,"posZ":3.0,"blockId":2},{"posX":1.0,"posY":0.0,"posZ":0.0,"blockId":2},{"posX":1.0,"posY":0.0,"posZ":1.0,"blockId":2},{"posX":1.0,"posY":0.0,"posZ":2.0,"blockId":2},{"posX":1.0,"posY":0.0,"posZ":3.0,"blockId":2},{"posX":1.0,"posY":1.0,"posZ":0.0,"blockId":2},{"posX":1.0,"posY":1.0,"posZ":1.0,"blockId":2},{"posX":1.0,"posY":1.0,"posZ":2.0,"blockId":2},{"posX":1.0,"posY":1.0,"posZ":3.0,"blockId":2},{"posX":1.0,"posY":2.0,"posZ":3.0,"blockId":1},{"posX":2.0,"posY":0.0,"posZ":0.0,"blockId":2},{"posX":2.0,"posY":0.0,"posZ":1.0,"blockId":2},{"posX":2.0,"posY":0.0,"posZ":2.0,"blockId":2},{"posX":2.0,"posY":0.0,"posZ":3.0,"blockId":2},{"posX":2.0,"posY":1.0,"posZ":0.0,"blockId":2},{"posX":2.0,"posY":1.0,"posZ":1.0,"blockId":2},{"posX":2.0,"posY":1.0,"posZ":2.0,"blockId":2},{"posX":2.0,"posY":1.0,"posZ":3.0,"blockId":2},{"posX":3.0,"posY":0.0,"posZ":0.0,"blockId":2},{"posX":3.0,"posY":0.0,"posZ":1.0,"blockId":2},{"posX":3.0,"posY":0.0,"posZ":2.0,"blockId":2},{"posX":3.0,"posY":0.0,"posZ":3.0,"blockId":2},{"posX":3.0,"posY":1.0,"posZ":0.0,"blockId":2},{"posX":3.0,"posY":1.0,"posZ":1.0,"blockId":2},{"posX":3.0,"posY":1.0,"posZ":2.0,"blockId":2},{"posX":3.0,"posY":1.0,"posZ":3.0,"blockId":2},{"posX":4.0,"posY":0.0,"posZ":0.0,"blockId":2},{"posX":4.0,"posY":0.0,"posZ":1.0,"blockId":2},{"posX":4.0,"posY":0.0,"posZ":2.0,"blockId":2},{"posX":4.0,"posY":0.0,"posZ":3.0,"blockId":2},{"posX":4.0,"posY":1.0,"posZ":0.0,"blockId":2},{"posX":4.0,"posY":1.0,"posZ":1.0,"blockId":2},{"posX":4.0,"posY":1.0,"posZ":2.0,"blockId":2},{"posX":4.0,"posY":1.0,"posZ":3.0,"blockId":2},{"posX":5.0,"posY":0.0,"posZ":0.0,"blockId":2},{"posX":5.0,"posY":0.0,"posZ":1.0,"blockId":2},{"posX":5.0,"posY":0.0,"posZ":2.0,"blockId":2},{"posX":5.0,"posY":0.0,"posZ":3.0,"blockId":2},{"posX":5.0,"posY":1.0,"posZ":0.0,"blockId":2},{"posX":5.0,"posY":1.0,"posZ":1.0,"blockId":2},{"posX":5.0,"posY":1.0,"posZ":2.0,"blockId":2},{"posX":5.0,"posY":1.0,"posZ":3.0,"blockId":2},{"posX":6.0,"posY":0.0,"posZ":0.0,"blockId":2},{"posX":6.0,"posY":0.0,"posZ":1.0,"blockId":2},{"posX":6.0,"posY":0.0,"posZ":2.0,"blockId":2},{"posX":6.0,"posY":0.0,"posZ":3.0,"blockId":2},{"posX":6.0,"posY":1.0,"posZ":0.0,"blockId":2},{"posX":6.0,"posY":1.0,"posZ":1.0,"blockId":2},{"posX":6.0,"posY":1.0,"posZ":2.0,"blockId":2},{"posX":6.0,"posY":1.0,"posZ":3.0,"blockId":2}]},"createDate":"2025-01-22T17:43:00.485332+00:00","nameBuilding":"Шедеврище - 86","guid":"ec56c70c-6b46-457e-9076-b0e2416d5d77","playersLiked":["Скиталец 065"]}